<?xml version="1.0" encoding="utf-8"?>
<publishData>
  <publishProfile publishUrl="C:\Inetpub\wwwroot\idbmaps" deleteExistingFiles="False" ftpAnonymousLogin="False" ftpPassiveMode="True" msdeploySite="IDBMaps" msdeploySiteID="" msdeployRemoteSitePhysicalPath="" msdeployAllowUntrustedCertificate="False" msdeploySkipExtraFilesOnServer="True" msdeployMarkAsApp="False" profileName="Profile1" publishMethod="FileSystem" replaceMatchingFiles="True" userName="" savePWD="False" userPWD="" SelectedForPublish="True">
    <file relUrl="Content/maps/Inter-American-Development-Bank-HQ-5.png" publishTime="08/18/2014 16:56:48" />
    <file relUrl="Content/themes/base/minified/jquery.ui.datepicker.min.css" publishTime="08/06/2014 09:56:51" />
    <file relUrl="bin/Content/dxf/IDB-8.dxf" publishTime="09/04/2014 13:42:25" />
    <file relUrl="Content/themes/base/minified/jquery.ui.slider.min.css" publishTime="08/06/2014 09:56:51" />
    <file relUrl="bin/Antlr3.Runtime.dll" publishTime="08/06/2014 09:56:56" />
    <file relUrl="bin/System.Web.Providers.dll" publishTime="08/06/2014 09:56:55" />
    <file relUrl="bin/Content/maps/Inter-American-Development-Bank-HQ-4.png" publishTime="08/18/2014 15:57:20" />
    <file relUrl="Content/maps/IDB-6.png" publishTime="11/14/2014 14:51:44" />
    <file relUrl="bin/Content/maps/IDB-8.png" publishTime="11/14/2014 14:52:08" />
    <file relUrl="Content/themes/base/jquery.ui.datepicker.css" publishTime="08/06/2014 09:56:51" />
    <file relUrl="bin/System.Web.Helpers.xml" publishTime="08/06/2014 09:56:53" />
    <file relUrl="bin/Content/maps/Inter-American-Development-Bank-HQ-3.png" publishTime="10/27/2014 13:10:21" />
    <file relUrl="Content/dxf/IDB-11.dxf" publishTime="09/04/2014 13:41:51" />
    <file relUrl="Content/themes/base/minified/jquery-ui.min.css" publishTime="08/06/2014 09:56:51" />
    <file relUrl="Scripts/jquery.unobtrusive-ajax.js" publishTime="08/06/2014 09:56:52" />
    <file relUrl="Content/themes/base/minified/jquery.ui.autocomplete.min.css" publishTime="08/06/2014 09:56:51" />
    <file relUrl="bin/Microsoft.Web.Infrastructure.dll" publishTime="08/06/2014 09:56:52" />
    <file relUrl="bin/Content/maps/Inter-American-Development-Bank-HQ-7.png" publishTime="08/18/2014 17:10:25" />
    <file relUrl="Content/themes/base/images/ui-bg_highlight-soft_75_cccccc_1x100.png" publishTime="08/06/2014 09:56:52" />
    <file relUrl="Content/themes/base/jquery.ui.slider.css" publishTime="08/06/2014 09:56:51" />
    <file relUrl="bin/System.Web.WebPages.dll" publishTime="08/06/2014 09:56:53" />
    <file relUrl="Content/maps/Inter-American-Development-Bank-HQ-3.png" publishTime="10/27/2014 13:10:21" />
    <file relUrl="bin/Content/dxf/IDB-5.dxf" publishTime="09/04/2014 13:42:12" />
    <file relUrl="Content/themes/base/jquery.ui.selectable.css" publishTime="08/06/2014 09:56:51" />
    <file relUrl="Content/themes/base/minified/images/ui-icons_222222_256x240.png" publishTime="08/06/2014 09:56:51" />
    <file relUrl="Scripts/jquery.validate.js" publishTime="08/06/2014 09:56:50" />
    <file relUrl="bin/System.Web.Razor.xml" publishTime="08/06/2014 09:56:53" />
    <file relUrl="bin/System.Net.Http.xml" publishTime="08/06/2014 09:56:54" />
    <file relUrl="bin/System.Web.WebPages.Razor.xml" publishTime="08/06/2014 09:56:53" />
    <file relUrl="Content/themes/base/jquery.ui.all.css" publishTime="08/06/2014 09:56:51" />
    <file relUrl="bin/Content/maps/IDB-9.png" publishTime="11/14/2014 14:52:22" />
    <file relUrl="bin/System.Web.Razor.dll" publishTime="08/06/2014 09:56:53" />
    <file relUrl="Images/test.jpg" publishTime="08/12/2014 15:28:49" />
    <file relUrl="Views/Home/Index.cshtml" publishTime="11/18/2014 10:42:35" />
    <file relUrl="bin/System.Net.Http.Formatting.xml" publishTime="10/03/2014 12:02:36" />
    <file relUrl="Views/Shared/Error.cshtml" publishTime="08/06/2014 09:56:39" />
    <file relUrl="bin/Content/maps/Inter-American-Development-Bank-HQ-9.png" publishTime="08/18/2014 17:15:43" />
    <file relUrl="Content/themes/base/minified/jquery.ui.progressbar.min.css" publishTime="08/06/2014 09:56:51" />
    <file relUrl="Scripts/jquery-1.7.1.min.js" publishTime="08/06/2014 09:56:50" />
    <file relUrl="Content/dxf/IDB-2.dxf" publishTime="09/04/2014 13:41:57" />
    <file relUrl="bin/Content/dxf/IDB10.dxf" publishTime="09/04/2014 13:41:42" />
    <file relUrl="bin/Content/dxf/IDB-6.dxf" publishTime="09/04/2014 13:42:16" />
    <file relUrl="Scripts/jquery-1.7.1.js" publishTime="08/06/2014 09:56:50" />
    <file relUrl="bin/Simple.Data.Ado.dll" publishTime="08/06/2014 10:14:48" />
    <file relUrl="Content/maps/IDB-7.png" publishTime="11/14/2014 14:51:57" />
    <file relUrl="bin/Content/maps/IDB-3.png" publishTime="11/14/2014 14:51:06" />
    <file relUrl="Content/maps/Inter-American-Development-Bank-HQ-11.png" publishTime="08/18/2014 17:20:53" />
    <file relUrl="bin/Content/dxf/IDB-11.dxf" publishTime="09/04/2014 13:41:51" />
    <file relUrl="bin/Microsoft.Exchange.WebServices.dll" publishTime="08/11/2014 11:50:41" />
    <file relUrl="Content/themes/base/minified/jquery.ui.accordion.min.css" publishTime="08/06/2014 09:56:51" />
    <file relUrl="Content/themes/base/jquery-ui.css" publishTime="08/06/2014 09:56:51" />
    <file relUrl="Content/themes/base/jquery.ui.resizable.css" publishTime="08/06/2014 09:56:51" />
    <file relUrl="Content/themes/base/images/ui-bg_glass_55_fbf9ee_1x400.png" publishTime="08/06/2014 09:56:52" />
    <file relUrl="bin/System.Net.Http.Formatting.dll" publishTime="10/03/2014 12:02:36" />
    <file relUrl="Content/themes/base/jquery.ui.tabs.css" publishTime="08/06/2014 09:56:51" />
    <file relUrl="bin/System.Web.WebPages.xml" publishTime="08/06/2014 09:56:53" />
    <file relUrl="Scripts/knockout-2.1.0.debug.js" publishTime="08/06/2014 09:56:56" />
    <file relUrl="bin/Content/maps/Inter-American-Development-Bank-HQ-8.png" publishTime="08/18/2014 17:12:55" />
    <file relUrl="bin/PdfSharp.pdb" publishTime="02/22/2015 12:29:43" />
    <file relUrl="Content/maps/IDB-3.png" publishTime="11/14/2014 14:51:06" />
    <file relUrl="Content/themes/base/images/ui-icons_2e83ff_256x240.png" publishTime="08/06/2014 09:56:52" />
    <file relUrl="Content/themes/base/minified/jquery.ui.tabs.min.css" publishTime="08/06/2014 09:56:51" />
    <file relUrl="Content/maps/IDB-8.png" publishTime="11/14/2014 14:52:08" />
    <file relUrl="Content/maps/IDB-1.png" publishTime="11/14/2014 14:50:41" />
    <file relUrl="Scripts/_references.js" publishTime="08/06/2014 09:56:39" />
    <file relUrl="bin/System.Web.WebPages.Deployment.dll" publishTime="08/06/2014 09:56:53" />
    <file relUrl="bin/Content/dxf/IDB-9.dxf" publishTime="09/04/2014 13:42:28" />
    <file relUrl="bin/Newtonsoft.Json.dll" publishTime="10/03/2014 12:02:36" />
    <file relUrl="Content/maps/Inter-American-Development-Bank-HQ-7.png" publishTime="08/18/2014 17:10:25" />
    <file relUrl="Scripts/jquery-ui-1.8.20.min.js" publishTime="08/06/2014 09:56:51" />
    <file relUrl="Content/maps/Inter-American-Development-Bank-HQ-0.png" publishTime="08/18/2014 15:45:08" />
    <file relUrl="bin/Content/maps/Inter-American-Development-Bank-HQ-11.png" publishTime="08/18/2014 17:20:53" />
    <file relUrl="bin/Simple.Data.SqlServer.dll" publishTime="08/06/2014 10:15:02" />
    <file relUrl="Global.asax" publishTime="08/06/2014 09:56:39" />
    <file relUrl="bin/EntityFramework.xml" publishTime="08/06/2014 09:56:44" />
    <file relUrl="Content/dxf/IDB-7.dxf" publishTime="09/04/2014 13:42:21" />
    <file relUrl="Content/maps/Inter-American-Development-Bank-HQ-9.png" publishTime="08/18/2014 17:15:43" />
    <file relUrl="Content/maps/IDB-5.png" publishTime="11/14/2014 14:51:32" />
    <file relUrl="Views/_ViewStart.cshtml" publishTime="08/06/2014 09:56:39" />
    <file relUrl="Content/dxf/IDB-1.dxf" publishTime="09/04/2014 13:42:36" />
    <file relUrl="Content/themes/base/minified/jquery.ui.theme.min.css" publishTime="08/06/2014 09:56:51" />
    <file relUrl="Web.config" publishTime="02/22/2015 14:45:28" />
    <file relUrl="Content/maps/Inter-American-Development-Bank-HQ-4.png" publishTime="08/18/2014 15:57:20" />
    <file relUrl="Content/themes/base/minified/jquery.ui.dialog.min.css" publishTime="08/06/2014 09:56:51" />
    <file relUrl="bin/Content/dxf/IDB-0.dxf" publishTime="09/04/2014 13:42:33" />
    <file relUrl="bin/Content/maps/Inter-American-Development-Bank-HQ-10.png" publishTime="08/18/2014 17:17:46" />
    <file relUrl="packages.config" publishTime="08/11/2014 11:50:41" />
    <file relUrl="bin/System.Web.Http.WebHost.dll" publishTime="08/06/2014 09:56:55" />
    <file relUrl="bin/Content/dxf/IDB-12.dxf" publishTime="09/04/2014 13:41:55" />
    <file relUrl="Content/themes/base/jquery.ui.dialog.css" publishTime="08/06/2014 09:56:51" />
    <file relUrl="bin/Content/maps/IDB-0.png" publishTime="11/14/2014 14:50:26" />
    <file relUrl="bin/Newtonsoft.Json.xml" publishTime="10/03/2014 12:02:36" />
    <file relUrl="Content/themes/base/minified/images/ui-icons_2e83ff_256x240.png" publishTime="08/06/2014 09:56:51" />
    <file relUrl="Content/dxf/IDB10.dxf" publishTime="09/04/2014 13:41:42" />
    <file relUrl="bin/Content/maps/IDB-7.png" publishTime="11/14/2014 14:51:57" />
    <file relUrl="Content/themes/base/minified/images/ui-bg_glass_55_fbf9ee_1x400.png" publishTime="08/06/2014 09:56:51" />
    <file relUrl="Content/themes/base/images/ui-icons_222222_256x240.png" publishTime="08/06/2014 09:56:52" />
    <file relUrl="Content/themes/base/minified/images/ui-icons_cd0a0a_256x240.png" publishTime="08/06/2014 09:56:51" />
    <file relUrl="Content/themes/base/minified/images/ui-bg_highlight-soft_75_cccccc_1x100.png" publishTime="08/06/2014 09:56:51" />
    <file relUrl="bin/itextsharp.dll" publishTime="08/12/2014 09:37:52" />
    <file relUrl="Scripts/jquery.validate.unobtrusive.min.js" publishTime="08/06/2014 09:56:52" />
    <file relUrl="bin/System.Web.Mvc.xml" publishTime="08/06/2014 09:56:54" />
    <file relUrl="bin/Content/pdf/IDB.pdf" publishTime="08/28/2014 17:27:00" />
    <file relUrl="Content/themes/base/minified/images/ui-bg_glass_75_e6e6e6_1x400.png" publishTime="08/06/2014 09:56:51" />
    <file relUrl="bin/Simple.Data.dll" publishTime="08/06/2014 10:14:48" />
    <file relUrl="bin/Content/dxf/IDB-3.dxf" publishTime="09/04/2014 13:42:02" />
    <file relUrl="Content/dxf/IDB-5.dxf" publishTime="09/04/2014 13:42:12" />
    <file relUrl="Content/themes/base/jquery.ui.autocomplete.css" publishTime="08/06/2014 09:56:51" />
    <file relUrl="bin/Content/maps/IDB-2.png" publishTime="11/14/2014 14:50:53" />
    <file relUrl="bin/Content/maps/IDB-1.png" publishTime="11/14/2014 14:50:41" />
    <file relUrl="bin/Content/maps/Inter-American-Development-Bank-HQ-2.png" publishTime="10/27/2014 12:50:49" />
    <file relUrl="bin/de/PdfSharp.resources.dll" publishTime="02/22/2015 12:29:43" />
    <file relUrl="Content/dxf/IDB-6.dxf" publishTime="09/04/2014 13:42:16" />
    <file relUrl="favicon.ico" publishTime="08/06/2014 09:56:39" />
    <file relUrl="Content/themes/base/minified/images/ui-bg_glass_65_ffffff_1x400.png" publishTime="08/06/2014 09:56:51" />
    <file relUrl="Scripts/jquery.validate-vsdoc.js" publishTime="08/06/2014 09:56:50" />
    <file relUrl="Content/themes/base/jquery.ui.theme.css" publishTime="08/06/2014 09:56:51" />
    <file relUrl="bin/Content/dxf/IDB-4.dxf" publishTime="09/04/2014 13:42:10" />
    <file relUrl="Content/themes/base/images/ui-bg_glass_95_fef1ec_1x400.png" publishTime="08/06/2014 09:56:52" />
    <file relUrl="Content/themes/base/minified/images/ui-bg_glass_75_dadada_1x400.png" publishTime="08/06/2014 09:56:51" />
    <file relUrl="Content/dxf/IDB-0.dxf" publishTime="09/04/2014 13:42:33" />
    <file relUrl="Content/maps/IDB-11.png" publishTime="11/14/2014 14:52:42" />
    <file relUrl="bin/WebAPI.OutputCache.dll" publishTime="10/03/2014 12:02:36" />
    <file relUrl="Scripts/jquery-1.7.1-vsdoc.js" publishTime="08/06/2014 09:56:50" />
    <file relUrl="bin/System.Net.Http.WebRequest.xml" publishTime="08/06/2014 09:56:54" />
    <file relUrl="Content/themes/base/images/ui-bg_glass_75_dadada_1x400.png" publishTime="08/06/2014 09:56:52" />
    <file relUrl="Content/themes/base/images/ui-icons_454545_256x240.png" publishTime="08/06/2014 09:56:52" />
    <file relUrl="Content/themes/base/jquery.ui.button.css" publishTime="08/06/2014 09:56:51" />
    <file relUrl="bin/System.Web.Optimization.dll" publishTime="08/06/2014 09:56:56" />
    <file relUrl="Content/themes/base/minified/images/ui-icons_888888_256x240.png" publishTime="08/06/2014 09:56:51" />
    <file relUrl="Content/dxf/IDB-12.dxf" publishTime="09/04/2014 13:41:55" />
    <file relUrl="bin/Content/maps/IDB-10.png" publishTime="11/14/2014 14:52:31" />
    <file relUrl="Content/maps/IDB-9.png" publishTime="11/14/2014 14:52:22" />
    <file relUrl="Content/themes/base/images/ui-bg_glass_65_ffffff_1x400.png" publishTime="08/06/2014 09:56:52" />
    <file relUrl="bin/IDBMaps.pdb" publishTime="02/22/2015 14:45:26" />
    <file relUrl="bin/Content/maps/IDB-4.png" publishTime="11/14/2014 14:51:21" />
    <file relUrl="Views/Shared/_Layout.cshtml" publishTime="12/16/2014 14:15:16" />
    <file relUrl="Content/themes/base/minified/images/ui-bg_flat_75_ffffff_40x100.png" publishTime="08/06/2014 09:56:51" />
    <file relUrl="Content/themes/base/minified/images/ui-bg_glass_95_fef1ec_1x400.png" publishTime="08/06/2014 09:56:51" />
    <file relUrl="bin/PdfSharp.xml" publishTime="02/22/2015 12:29:42" />
    <file relUrl="Content/themes/base/images/ui-icons_cd0a0a_256x240.png" publishTime="08/06/2014 09:56:51" />
    <file relUrl="bin/WebGrease.dll" publishTime="08/06/2014 09:56:56" />
    <file relUrl="Content/maps/Inter-American-Development-Bank-HQ-2.png" publishTime="10/27/2014 12:50:49" />
    <file relUrl="Content/themes/base/jquery.ui.accordion.css" publishTime="08/06/2014 09:56:51" />
    <file relUrl="Images/Marker.png" publishTime="08/12/2014 17:14:28" />
    <file relUrl="bin/Content/dxf/IDB-1.dxf" publishTime="09/04/2014 13:42:36" />
    <file relUrl="Content/themes/base/images/ui-bg_flat_0_aaaaaa_40x100.png" publishTime="08/06/2014 09:56:52" />
    <file relUrl="bin/Content/maps/IDB-12.png" publishTime="11/14/2014 14:52:53" />
    <file relUrl="bin/Content/maps/IDB-11.png" publishTime="11/14/2014 14:52:42" />
    <file relUrl="Content/themes/base/minified/images/ui-icons_454545_256x240.png" publishTime="08/06/2014 09:56:51" />
    <file relUrl="Content/themes/base/minified/jquery.ui.resizable.min.css" publishTime="08/06/2014 09:56:51" />
    <file relUrl="bin/Content/maps/IDB-6.png" publishTime="11/14/2014 14:51:44" />
    <file relUrl="Content/themes/base/minified/jquery.ui.core.min.css" publishTime="08/06/2014 09:56:51" />
    <file relUrl="Content/themes/base/images/ui-bg_flat_75_ffffff_40x100.png" publishTime="08/06/2014 09:56:52" />
    <file relUrl="bin/Content/maps/IDB-5.png" publishTime="11/14/2014 14:51:32" />
    <file relUrl="bin/Content/maps/Inter-American-Development-Bank-HQ-1.png" publishTime="10/27/2014 12:34:44" />
    <file relUrl="Scripts/knockout-2.1.0.js" publishTime="08/06/2014 09:56:56" />
    <file relUrl="Content/maps/Inter-American-Development-Bank-HQ-1.png" publishTime="10/27/2014 12:34:44" />
    <file relUrl="Content/themes/base/images/ui-icons_888888_256x240.png" publishTime="08/06/2014 09:56:52" />
    <file relUrl="bin/Content/maps/Inter-American-Development-Bank-HQ-6.png" publishTime="08/18/2014 17:07:18" />
    <file relUrl="Content/Site.css" publishTime="08/06/2014 09:56:39" />
    <file relUrl="Content/dxf/IDB-9.dxf" publishTime="09/04/2014 13:42:28" />
    <file relUrl="bin/PdfSharp.dll" publishTime="02/22/2015 12:29:43" />
    <file relUrl="bin/System.Web.WebPages.Razor.dll" publishTime="08/06/2014 09:56:53" />
    <file relUrl="Content/maps/IDB-2.png" publishTime="11/14/2014 14:50:53" />
    <file relUrl="bin/Content/dxf/IDB-2.dxf" publishTime="09/04/2014 13:41:57" />
    <file relUrl="bin/System.Web.Mvc.dll" publishTime="08/06/2014 09:56:54" />
    <file relUrl="bin/EntityFramework.dll" publishTime="08/06/2014 09:56:44" />
    <file relUrl="bin/System.Web.Http.WebHost.xml" publishTime="08/06/2014 09:56:55" />
    <file relUrl="Images/Maps/1.jpg" publishTime="08/06/2014 10:57:33" />
    <file relUrl="Scripts/jquery-ui-1.8.20.js" publishTime="08/06/2014 09:56:51" />
    <file relUrl="bin/System.Web.Http.dll" publishTime="10/03/2014 12:02:36" />
    <file relUrl="Scripts/modernizr-2.5.3.js" publishTime="08/06/2014 09:56:52" />
    <file relUrl="bin/WebApi.OutputCache.Core.dll" publishTime="10/03/2014 12:02:36" />
    <file relUrl="bin/Content/maps/Inter-American-Development-Bank-HQ-12.png" publishTime="08/18/2014 17:24:47" />
    <file relUrl="Content/maps/IDB-12.png" publishTime="11/14/2014 14:52:53" />
    <file relUrl="bin/Content/maps/Inter-American-Development-Bank-HQ-0.png" publishTime="08/18/2014 15:45:08" />
    <file relUrl="Content/themes/base/jquery.ui.progressbar.css" publishTime="08/06/2014 09:56:51" />
    <file relUrl="Content/themes/base/minified/jquery.ui.selectable.min.css" publishTime="08/06/2014 09:56:51" />
    <file relUrl="Content/maps/IDB-0.png" publishTime="11/14/2014 14:50:26" />
    <file relUrl="Content/themes/base/images/ui-bg_glass_75_e6e6e6_1x400.png" publishTime="08/06/2014 09:56:52" />
    <file relUrl="bin/Content/dxf/IDB-7.dxf" publishTime="09/04/2014 13:42:21" />
    <file relUrl="Content/dxf/IDB-8.dxf" publishTime="09/04/2014 13:42:25" />
    <file relUrl="bin/System.Net.Http.WebRequest.dll" publishTime="08/06/2014 09:56:54" />
    <file relUrl="bin/System.Web.Helpers.dll" publishTime="08/06/2014 09:56:53" />
    <file relUrl="Scripts/jquery.validate.unobtrusive.js" publishTime="08/06/2014 09:56:52" />
    <file relUrl="Content/maps/Inter-American-Development-Bank-HQ-6.png" publishTime="08/18/2014 17:07:18" />
    <file relUrl="Images/Maps/1.png" publishTime="08/06/2014 10:21:41" />
    <file relUrl="Views/Web.config" publishTime="08/06/2014 09:56:39" />
    <file relUrl="Content/themes/base/minified/images/ui-bg_flat_0_aaaaaa_40x100.png" publishTime="08/06/2014 09:56:51" />
    <file relUrl="bin/System.Web.Http.xml" publishTime="10/03/2014 12:02:36" />
    <file relUrl="Content/maps/Inter-American-Development-Bank-HQ-12.png" publishTime="08/18/2014 17:24:47" />
    <file relUrl="Scripts/jquery.validate.min.js" publishTime="08/06/2014 09:56:50" />
    <file relUrl="Content/maps/IDB-10.png" publishTime="11/14/2014 14:52:31" />
    <file relUrl="Content/maps/Inter-American-Development-Bank-HQ-10.png" publishTime="08/18/2014 17:17:46" />
    <file relUrl="Content/dxf/IDB-4.dxf" publishTime="09/04/2014 13:42:10" />
    <file relUrl="Content/themes/base/minified/jquery.ui.button.min.css" publishTime="08/06/2014 09:56:51" />
    <file relUrl="Scripts/jquery.unobtrusive-ajax.min.js" publishTime="08/06/2014 09:56:52" />
    <file relUrl="Content/themes/base/jquery.ui.core.css" publishTime="08/06/2014 09:56:51" />
    <file relUrl="Content/maps/Inter-American-Development-Bank-HQ-8.png" publishTime="08/18/2014 17:12:55" />
    <file relUrl="Content/themes/base/jquery.ui.base.css" publishTime="08/06/2014 09:56:51" />
    <file relUrl="Content/dxf/IDB-3.dxf" publishTime="09/04/2014 13:42:02" />
    <file relUrl="bin/System.Net.Http.dll" publishTime="08/06/2014 09:56:54" />
    <file relUrl="bin/Content/maps/Inter-American-Development-Bank-HQ-5.png" publishTime="08/18/2014 16:56:48" />
    <file relUrl="bin/IDBMaps.dll" publishTime="02/22/2015 14:45:27" />
    <file relUrl="Content/maps/IDB-4.png" publishTime="11/14/2014 14:51:21" />
    <file relUrl="bin/System.Web.WebPages.Deployment.xml" publishTime="08/06/2014 09:56:53" />
  </publishProfile>
</publishData>